rango_api/__init__.py
rango_api/cli.py
rango_api/core.py
rango_api/db.py
rango_api/generics.py
rango_api/middleware.py
rango_api/router.py
rango_api/serializers.py
rango_api/settings.py
rango_api-0.1.0.dist-info/licenses/LICENSE
rango_api-0.1.0.dist-info/METADATA
rango_api-0.1.0.dist-info/WHEEL
rango_api-0.1.0.dist-info/entry_points.txt
rango_api-0.1.0.dist-info/top_level.txt
rango_api-0.1.0.dist-info/RECORD
