Metadata-Version: 2.4
Name: rango-api
Version: 0.1.0
Summary: A modern Python web framework built on FastAPI with Django-like features and structure
Home-page: https://github.com/reshadMajumder/rango
Author: Jahidul Hassan Reshad
Author-email: Jahidul Hassan Reshad <hassanjahidul365@gmail.com>
License: MIT License
Project-URL: Homepage, https://github.com/reshadMajumder/rango
Project-URL: Documentation, https://github.com/reshadMajumder/rango#readme
Project-URL: Repository, https://github.com/reshadMajumder/rango
Project-URL: Issues, https://github.com/reshadMajumder/rango
Keywords: web,framework,fastapi,api,django-like
Classifier: Development Status :: 3 - Alpha
Classifier: Intended Audience :: Developers
Classifier: License :: OSI Approved :: MIT License
Classifier: Operating System :: OS Independent
Classifier: Programming Language :: Python :: 3
Classifier: Programming Language :: Python :: 3.8
Classifier: Programming Language :: Python :: 3.9
Classifier: Programming Language :: Python :: 3.10
Classifier: Programming Language :: Python :: 3.11
Classifier: Programming Language :: Python :: 3.12
Classifier: Topic :: Internet :: WWW/HTTP :: Dynamic Content
Classifier: Topic :: Software Development :: Libraries :: Application Frameworks
Classifier: Topic :: Software Development :: Libraries :: Python Modules
Requires-Python: >=3.8
License-File: LICENSE
Requires-Dist: aerich==0.9.2
Requires-Dist: aiosqlite==0.21.0
Requires-Dist: annotated-types==0.7.0
Requires-Dist: anyio==4.11.0
Requires-Dist: asyncclick==8.3.0.7
Requires-Dist: click==8.3.0
Requires-Dist: colorama==0.4.6
Requires-Dist: dictdiffer==0.9.0
Requires-Dist: fastapi==0.119.0
Requires-Dist: h11==0.16.0
Requires-Dist: idna==3.10
Requires-Dist: iso8601==2.1.0
Requires-Dist: markdown-it-py==4.0.0
Requires-Dist: mdurl==0.1.2
Requires-Dist: pydantic==2.12.0
Requires-Dist: pydantic_core==2.41.1
Requires-Dist: Pygments==2.19.2
Requires-Dist: pypika-tortoise==0.6.2
Requires-Dist: pytz==2025.2
Requires-Dist: rich==14.2.0
Requires-Dist: shellingham==1.5.4
Requires-Dist: sniffio==1.3.1
Requires-Dist: starlette==0.48.0
Requires-Dist: tortoise-orm==0.25.1
Requires-Dist: typer==0.19.2
Requires-Dist: typing-inspection==0.4.2
Requires-Dist: typing_extensions==4.15.0
Requires-Dist: uvicorn==0.37.0
Provides-Extra: dev
Requires-Dist: pytest>=6.0; extra == "dev"
Requires-Dist: pytest-asyncio; extra == "dev"
Requires-Dist: black; extra == "dev"
Requires-Dist: flake8; extra == "dev"
Requires-Dist: mypy; extra == "dev"
Dynamic: author
Dynamic: home-page
Dynamic: license-file
Dynamic: requires-python
